README.rst
setup.py
aioserialctrl/__init__.py
aioserialctrl/aioserialctrl.py
aioserialctrl/constants.py
aioserialctrl/exceptions.py
aioserialctrl/serialctrl.py
aioserialctrl/seriallib.c
aioserialctrl.egg-info/PKG-INFO
aioserialctrl.egg-info/SOURCES.txt
aioserialctrl.egg-info/dependency_links.txt
aioserialctrl.egg-info/top_level.txt
aioserialctrl/utils/ports.py