Metadata-Version: 2.1
Name: aioserialctrl
Version: 0.1.2
Summary: A module of asyncio serail port control.
Home-page: https://github.com/eplut/aioserialctrl
Author: eplut
Author-email: eplutus@protonmail.com
License: MIT
Keywords: serial serialctrl aioserialctrl
Platform: Windows
Classifier: Operating System :: Microsoft :: Windows
Classifier: Programming Language :: Python :: 3.7
Requires-Python: >=3.7
